{
  "properties": [
    {
      "name": "thymeleaf.content-type",
      "type": "java.lang.String",
      "description": "Description for thymeleaf.content-type."
    },
    {
      "name": "server.servlet.context-path",
      "type": "java.lang.String",
      "description": "Description for server.servlet.context-path."
    },
    {
      "name": "mybatis-plus.global-config.db-column-underline",
      "type": "java.lang.String",
      "description": "Description for mybatis-plus.global-config.db-column-underline."
    }
  ] }